pySSHS/__init__.py
pySSHS/sshs.py
pysshs-1.0.0.0.dist-info/METADATA
pysshs-1.0.0.0.dist-info/WHEEL
pysshs-1.0.0.0.dist-info/licenses/LICENSE
pysshs-1.0.0.0.dist-info/RECORD
