Metadata-Version: 2.4
Name: pySSHS
Version: 1.0.0.0
Summary: Scale-space histogram segmentation algorithm
Project-URL: Homepage, https://github.com/jegilles/pySSHS
Project-URL: Issues, https://github.com/jegilles/pySSHS/issues
Author-email: Jerome Gilles <jgilles@sdsu.edu>
License: MIT License
License-File: LICENSE
Classifier: Operating System :: OS Independent
Classifier: Programming Language :: Python :: 3
Requires-Python: >=3.8
